MANIFEST.in
README.rst
setup.cfg
setup.py
versioneer.py
libpuzzle/__init__.py
libpuzzle/_version.py
libpuzzle/bases.c
libpuzzle/objects.py
libpuzzle.egg-info/PKG-INFO
libpuzzle.egg-info/SOURCES.txt
libpuzzle.egg-info/dependency_links.txt
libpuzzle.egg-info/requires.txt
libpuzzle.egg-info/top_level.txt