Metadata-Version: 1.1
Name: libpuzzle
Version: 1.0.0
Summary: Quickly find visually similar images
Home-page: https://lab.errorist.xyz/py/libpuzzle
Author: Xavier Barbosa
Author-email: clint.northwood@gmail.com
License: MIT
Keywords: image
Platform: UNKNOWN
Classifier: Development Status :: 5 - Production/Stable
Classifier: License :: OSI Approved :: MIT License
Classifier: Programming Language :: Python :: 2.7
Classifier: Programming Language :: Python :: 3.4
Classifier: Programming Language :: Python :: 3.5
Classifier: Programming Language :: Python :: Implementation :: CPython
Classifier: Topic :: Software Development :: Libraries :: Python Modules
